greyalien/__init__.py
greyalien/__main__.py
greyalien/ast.py
greyalien/cli.py
greyalien/diagnostics.py
greyalien/interpreter.py
greyalien/lexer.py
greyalien/loader.py
greyalien/modules.py
greyalien/parser.py
greyalien/typechecker.py
greyalien/compiler/__init__.py
greyalien/compiler/__main__.py
greyalien/compiler/frontend.py
greyalien/compiler/ir.py
greyalien_prototype-0.3.1.dist-info/licenses/LICENSE
greyalien_prototype-0.3.1.dist-info/METADATA
greyalien_prototype-0.3.1.dist-info/WHEEL
greyalien_prototype-0.3.1.dist-info/entry_points.txt
greyalien_prototype-0.3.1.dist-info/top_level.txt
greyalien_prototype-0.3.1.dist-info/RECORD
