Metadata-Version: 2.4
Name: greyalien-prototype
Version: 0.3.1
Summary: Prototype interpreter and design docs for the Greyalien language.
Author: lexluger
License-Expression: MIT
Project-URL: Homepage, https://github.com/JROChub/greyalien-prototype
Project-URL: Repository, https://github.com/JROChub/greyalien-prototype
Project-URL: Issues, https://github.com/JROChub/greyalien-prototype/issues
Keywords: language,interpreter,compiler,greyalien
Classifier: Development Status :: 3 - Alpha
Classifier: Programming Language :: Python :: 3
Classifier: Programming Language :: Python :: 3 :: Only
Classifier: Programming Language :: Python :: 3.9
Classifier: Programming Language :: Python :: 3.10
Classifier: Programming Language :: Python :: 3.11
Classifier: Programming Language :: Python :: 3.12
Requires-Python: >=3.9
License-File: LICENSE
Provides-Extra: dev
Requires-Dist: coverage; extra == "dev"
Requires-Dist: mypy; extra == "dev"
Requires-Dist: ruff; extra == "dev"
Dynamic: license-file
